{
	"backtrace" : 5,
	"backtraceGraph" : 
	{
		"commands" : 
		[
			"add_custom_target",
			"find_package"
		],
		"files" : 
		[
			"/opt/ros/noetic/share/nav_msgs/cmake/nav_msgsConfig.cmake",
			"/opt/ros/noetic/share/catkin/cmake/catkinConfig.cmake",
			"ekf_localization_node_pkg/CMakeLists.txt"
		],
		"nodes" : 
		[
			{
				"file" : 2
			},
			{
				"command" : 1,
				"file" : 2,
				"line" : 10,
				"parent" : 0
			},
			{
				"file" : 1,
				"parent" : 1
			},
			{
				"command" : 1,
				"file" : 1,
				"line" : 76,
				"parent" : 2
			},
			{
				"file" : 0,
				"parent" : 3
			},
			{
				"command" : 0,
				"file" : 0,
				"line" : 186,
				"parent" : 4
			}
		]
	},
	"id" : "nav_msgs_generate_messages_nodejs::@e5cd7ea110d1fa2b4aca",
	"name" : "nav_msgs_generate_messages_nodejs",
	"paths" : 
	{
		"build" : "ekf_localization_node_pkg",
		"source" : "ekf_localization_node_pkg"
	},
	"sources" : [],
	"type" : "UTILITY"
}
